LICENSE
MANIFEST.in
README.md
pyproject.toml
setup.cfg
setup.py
wtoolzargs/__init__.py
wtoolzargs/version.py
wtoolzargs.egg-info/PKG-INFO
wtoolzargs.egg-info/SOURCES.txt
wtoolzargs.egg-info/dependency_links.txt
wtoolzargs.egg-info/requires.txt
wtoolzargs.egg-info/top_level.txt
wtoolzargs/common/__init__.py
wtoolzargs/common/astprinter.py
wtoolzargs/common/exceptions.py
wtoolzargs/common/expressions.py
wtoolzargs/common/token_.py
wtoolzargs/common/utils.py
wtoolzargs/filtering/__init__.py
wtoolzargs/filtering/interpreter.py
wtoolzargs/filtering/parser.py
wtoolzargs/filtering/scanner.py
wtoolzargs/filtering/tokentype.py
wtoolzargs/ordering/__init__.py
wtoolzargs/ordering/interpreter.py
wtoolzargs/ordering/parser.py
wtoolzargs/ordering/scanner.py
wtoolzargs/ordering/tokentype.py